CHANGELOG.md
MANIFEST.in
README.md
setup.cfg
setup.py
versioneer.py
src/libreflow/__init__.py
src/libreflow.extensions.test.import_files.egg-info/PKG-INFO
src/libreflow.extensions.test.import_files.egg-info/SOURCES.txt
src/libreflow.extensions.test.import_files.egg-info/dependency_links.txt
src/libreflow.extensions.test.import_files.egg-info/top_level.txt
src/libreflow/extensions/__init__.py
src/libreflow/extensions/test/__init__.py
src/libreflow/extensions/test/import_files/__init__.py
src/libreflow/extensions/test/import_files/_version.py